MANIFEST.in
README.rst
VERSION
setup.cfg
setup.py
test/test_dialog.py
test/test_palette.py
urwid_utils/__init__.py
urwid_utils/colors.py
urwid_utils/const.py
urwid_utils/dialog.py
urwid_utils/keys.py
urwid_utils/palette.py
urwid_utils/util.py
urwid_utils.egg-info/PKG-INFO
urwid_utils.egg-info/SOURCES.txt
urwid_utils.egg-info/dependency_links.txt
urwid_utils.egg-info/top_level.txt