Metadata-Version: 1.1
Name: urwid-utils
Version: 0.0.4
Summary: A collection of simple, straightforward, but extensible utilities for the urwid package.
Home-page: https://github.com/stnbu/urwid_utils
Author: Mike Burr
Author-email: mburr@unintuitive.org
License: MIT
Download-URL: https://github.com/stnbu/urwid_utils/archive/master.zip
Platform: UNKNOWN
Classifier: Development Status :: 3 - Alpha
Classifier: Environment :: Console :: Curses
Classifier: Intended Audience :: Developers
Classifier: License :: OSI Approved :: MIT License
Classifier: Programming Language :: Python :: 2
Classifier: Topic :: Software Development :: User Interfaces
Classifier: Topic :: Software Development :: Widget Sets
Classifier: Topic :: Software Development
Classifier: Topic :: Utilities
Requires: urwid
Provides: urwid_utils
